autrain/__init__.py
autrain/checker.py
autrain-0.0.2.dist-info/METADATA
autrain-0.0.2.dist-info/WHEEL
autrain-0.0.2.dist-info/top_level.txt
autrain-0.0.2.dist-info/RECORD
