Metadata-Version: 2.1
Name: autrain
Version: 0.0.2
Summary: A basic package for support autotraining
Author: tuclen3
Author-email: <tung.nguyen158minh@hcmut.edu.vn>
Keywords: python,video,stream,autotrain
Classifier: Development Status :: 1 - Planning
Classifier: Intended Audience :: Developers
Classifier: Programming Language :: Python :: 3
Classifier: Operating System :: Unix
Classifier: Operating System :: MacOS :: MacOS X
Classifier: Operating System :: Microsoft :: Windows
